LICENSE
README.md
setup.cfg
setup.py
zeno/__init__.py
zeno/enum.py
zeno/zeno_client.py
zeno/abis/AdaptiveFeeCalculator.json
zeno/abis/Calculator.json
zeno/abis/CixPriceAdapter.json
zeno/abis/ConfigStorage.json
zeno/abis/CrossMarginHandler.json
zeno/abis/ERC20.json
zeno/abis/LimitTradeHandler.json
zeno/abis/OnChainPriceLens.json
zeno/abis/OracleMiddleware.json
zeno/abis/OrderbookOracle.json
zeno/abis/PerpStorage.json
zeno/abis/TradeHelper.json
zeno/abis/VaultStorage.json
zeno/constants/__init__.py
zeno/constants/assets.py
zeno/constants/common.py
zeno/constants/contracts.py
zeno/constants/intent.py
zeno/constants/markets.py
zeno/constants/pricefeed.py
zeno/constants/tokens.py
zeno/helpers/__init__.py
zeno/helpers/contract_loader.py
zeno/helpers/mapper.py
zeno/helpers/util.py
zeno/modules/__init__.py
zeno/modules/private.py
zeno/modules/public.py
zeno/modules/calculator/__init__.py
zeno/modules/calculator/calculator.py
zeno/modules/oracle/__init__.py
zeno/modules/oracle/oracle_middleware.py
zeno/modules/oracle/cix_oracle/__init__.py
zeno/modules/oracle/cix_oracle/cix_oracle.py
zeno/modules/oracle/onchain_pricelens_oracle/__init__.py
zeno/modules/oracle/onchain_pricelens_oracle/onchain_pricelen_oracle.py
zeno/modules/oracle/pyth_oracle/__init__.py
zeno/modules/oracle/pyth_oracle/pyth_oracle.py
zeno_python_sdk.egg-info/PKG-INFO
zeno_python_sdk.egg-info/SOURCES.txt
zeno_python_sdk.egg-info/dependency_links.txt
zeno_python_sdk.egg-info/requires.txt
zeno_python_sdk.egg-info/top_level.txt