Metadata-Version: 2.1
Name: zeno-python-sdk
Version: 0.0.2
Summary: Zeno Python SDK
Home-page: https://github.com/Zeno-Exchange/zeno-sdk
Author: ZenoExchange
License: MIT
Keywords: zeno exchange perp dex defi ethereum eth metis
Classifier: Intended Audience :: Developers
Classifier: License :: OSI Approved :: MIT License
Classifier: Operating System :: OS Independent
Classifier: Programming Language :: Python :: 2
Classifier: Programming Language :: Python :: 2.7
Classifier: Programming Language :: Python :: 3
Classifier: Programming Language :: Python :: 3.4
Classifier: Programming Language :: Python :: 3.5
Classifier: Programming Language :: Python :: 3.6
Classifier: Programming Language :: Python :: 3.9
Classifier: Programming Language :: Python :: 3.11
Classifier: Programming Language :: Python
Classifier: Topic :: Software Development :: Libraries :: Python Modules
License-File: LICENSE
